pyfatfs/BootSectorHeader.py
pyfatfs/DosDateTime.py
pyfatfs/EightDotThree.py
pyfatfs/FATDirectoryEntry.py
pyfatfs/FSInfo.py
pyfatfs/FatIO.py
pyfatfs/PyFat.py
pyfatfs/PyFatFS.py
pyfatfs/PyFatFSOpener.py
pyfatfs/__init__.py
pyfatfs/_exceptions.py
pyfatfs-1.1.0.dist-info/LICENSE
pyfatfs-1.1.0.dist-info/METADATA
pyfatfs-1.1.0.dist-info/WHEEL
pyfatfs-1.1.0.dist-info/entry_points.txt
pyfatfs-1.1.0.dist-info/top_level.txt
pyfatfs-1.1.0.dist-info/RECORD
