Metadata-Version: 2.1
Name: pyfatfs
Version: 1.1.0
Summary: FAT12/FAT16/FAT32 implementation with VFAT support
Author-email: "Nathan-J. Hirschauer" <nathanhi@deepserve.info>
License: MIT License
Project-URL: Homepage, https://github.com/nathanhi/pyfatfs
Project-URL: Documentation, https://pyfatfs.readthedocs.io
Project-URL: Changelog, https://github.com/nathanhi/pyfatfs/blob/master/CHANGELOG.rst
Project-URL: Issues, https://github.com/nathanhi/pyfatfs/issues
Project-URL: Source, https://github.com/nathanhi/pyfatfs
Keywords: filesystem,PyFilesystem2,FAT12,FAT16,FAT32,VFAT,LFN
Classifier: Development Status :: 5 - Production/Stable
Classifier: Intended Audience :: Developers
Classifier: License :: OSI Approved :: MIT License
Classifier: Operating System :: OS Independent
Classifier: Programming Language :: Python :: 3
Classifier: Programming Language :: Python :: 3 :: Only
Classifier: Topic :: Software Development :: Libraries
Classifier: Topic :: Software Development :: Libraries :: Python Modules
Classifier: Topic :: System :: Filesystems
Requires-Python: ~=3.8
Provides-Extra: development
License-File: LICENSE
